proxymlosy/__init__.py
proxymlosy/sender.py
proxymlosy-0.1.1.dist-info/METADATA
proxymlosy-0.1.1.dist-info/WHEEL
proxymlosy-0.1.1.dist-info/top_level.txt
proxymlosy-0.1.1.dist-info/RECORD
